odoo/addons/spec_driven_model/README.rst
odoo/addons/spec_driven_model/__init__.py
odoo/addons/spec_driven_model/__manifest__.py
odoo/addons/spec_driven_model/i18n/pt_BR.po
odoo/addons/spec_driven_model/i18n/spec_driven_model.pot
odoo/addons/spec_driven_model/models/__init__.py
odoo/addons/spec_driven_model/models/spec_export.py
odoo/addons/spec_driven_model/models/spec_import.py
odoo/addons/spec_driven_model/models/spec_mixin.py
odoo/addons/spec_driven_model/models/spec_models.py
odoo/addons/spec_driven_model/models/spec_view.py
odoo/addons/spec_driven_model/readme/CONFIGURE.rst
odoo/addons/spec_driven_model/readme/CONTRIBUTORS.rst
odoo/addons/spec_driven_model/readme/DESCRIPTION.rst
odoo/addons/spec_driven_model/readme/HISTORY.rst
odoo/addons/spec_driven_model/readme/INSTALL.rst
odoo/addons/spec_driven_model/readme/ROADMAP.rst
odoo/addons/spec_driven_model/readme/USAGE.rst
odoo/addons/spec_driven_model/static/description/icon.png
odoo/addons/spec_driven_model/static/description/index.html
odoo/addons/spec_driven_model/tests/PurchaseOrderSchema.xsd
odoo/addons/spec_driven_model/tests/__init__.py
odoo/addons/spec_driven_model/tests/fake_mixin.py
odoo/addons/spec_driven_model/tests/fake_odoo_purchase.py
odoo/addons/spec_driven_model/tests/purchase_order_lib.py
odoo/addons/spec_driven_model/tests/spec_poxsd.py
odoo/addons/spec_driven_model/tests/spec_purchase.py
odoo/addons/spec_driven_model/tests/test_spec_model.py
odoo14_addon_spec_driven_model-14.0.6.1.0.dist-info/METADATA
odoo14_addon_spec_driven_model-14.0.6.1.0.dist-info/WHEEL
odoo14_addon_spec_driven_model-14.0.6.1.0.dist-info/top_level.txt
odoo14_addon_spec_driven_model-14.0.6.1.0.dist-info/RECORD
